

[
  
  
    {
      "title"    : "页面没有找到",
      "url"      : "https://bran-nie.github.io/404.html",
      "keywords" : "404"
    } ,
  
  
  
    {
      "title"    : "About",
      "url"      : "https://bran-nie.github.io/about/",
      "keywords" : "Zhuang Ma, 马壮"
    } ,
  
  
  
    {
      "title"    : "归档",
      "url"      : "https://bran-nie.github.io/archives/",
      "keywords" : "归档"
    } ,
  
  
  
    {
      "title"    : "Categories",
      "url"      : "https://bran-nie.github.io/categories/",
      "keywords" : "分类"
    } ,
  
  
  
  
  
    {
      "title"    : "Links",
      "url"      : "https://bran-nie.github.io/links/",
      "keywords" : "友情链接"
    } ,
  
  
  
    {
      "title"    : "mindmap",
      "url"      : "https://bran-nie.github.io/mindmap-viewer/",
      "keywords" : "mindmap"
    } ,
  
  
  
    {
      "title"    : "Open Source Projects",
      "url"      : "https://bran-nie.github.io/open-source/",
      "keywords" : "开源,open-source,GitHub,开源项目"
    } ,
  
  
  
  
  
    {
      "title"    : "Wiki",
      "url"      : "https://bran-nie.github.io/wiki/",
      "keywords" : "维基, Wiki"
    } ,
  
  
  
  
  
  
  
  
  
  
  
  
  
  

  
    {
      "title"    : "Fcc --- steamrollArray",
      "category" : "Algorithm",
      
      "url"      : "https://bran-nie.github.io/2016/12/05/fcc-steamroller/",
      "keywords" : "keyword1, keyword2"
    } ,
  
    {
      "title"    : "Github 的注册与使用教程以及github page (一)",
      "category" : "Tutorials",
      
      "url"      : "https://bran-nie.github.io/2016/12/08/github-page-1/",
      "keywords" : "Github page"
    } ,
  
    {
      "title"    : "一次晚归夜宿与早起日出",
      "category" : "Life",
      
      "url"      : "https://bran-nie.github.io/2016/12/12/night/",
      "keywords" : ""
    } ,
  
    {
      "title"    : "Github 的注册与使用教程以及github page (二)",
      "category" : "Tutorials",
      
      "url"      : "https://bran-nie.github.io/2016/12/18/github-page-2/",
      "keywords" : "Github page"
    } ,
  
    {
      "title"    : "css3 一些样式",
      "category" : "Css",
      
      "url"      : "https://bran-nie.github.io/2016/12/19/css/",
      "keywords" : ""
    } ,
  
    {
      "title"    : "phantomjs———刷IFE琐记",
      "category" : "Tutorials",
      
      "url"      : "https://bran-nie.github.io/2017/03/04/ife-phantomjs/",
      "keywords" : "ife, phantomjs"
    } ,
  
    {
      "title"    : "360浏览器、QQ浏览器等 &lt;meta&gt; 标签选择webkit内核问题",
      "category" : "Tutorials",
      
      "url"      : "https://bran-nie.github.io/2017/05/05/brower_meta/",
      "keywords" : ""
    } ,
  
    {
      "title"    : "简单开启Mac下的服务器",
      "category" : "Tutorials",
      
      "url"      : "https://bran-nie.github.io/2018/08/02/mac-server/",
      "keywords" : "Mac 终端 本地服务器"
    } ,
  
    {
      "title"    : "ES6 --- Promise(简介)",
      "category" : "Javascript",
      
      "url"      : "https://bran-nie.github.io/2018/08/07/promise/",
      "keywords" : ""
    } ,
  
    {
      "title"    : "如何自然入睡",
      "category" : "Life",
      
      "url"      : "https://bran-nie.github.io/2018/08/13/easy-to-sleep/",
      "keywords" : ""
    } ,
  
    {
      "title"    : "Linux命令- - - scp 服务器间传输，基于ssh",
      "category" : "Tutorials",
      
      "url"      : "https://bran-nie.github.io/2018/09/18/commands-scp/",
      "keywords" : "Mac scp Linux 文件传输 服务器"
    } ,
  
    {
      "title"    : "查找范围内的素数 - 埃拉托斯特尼筛法",
      "category" : "Algorithm",
      
      "url"      : "https://bran-nie.github.io/2018/11/08/primes/",
      "keywords" : "primes"
    } ,
  
    {
      "title"    : "分析比较opacity:0、visibility:hidden、display:none的区别、优劣及适用场景",
      "category" : "Css",
      
      "url"      : "https://bran-nie.github.io/2019/04/18/css/",
      "keywords" : ""
    } ,
  
    {
      "title"    : "商品规格选择sku --- Vue版",
      "category" : "Javascript",
      
      "url"      : "https://bran-nie.github.io/2019/05/07/sku/",
      "keywords" : ""
    } ,
  
    {
      "title"    : "两个链表相加",
      "category" : "Algorithm",
      
      "url"      : "https://bran-nie.github.io/2019/05/23/two-linklist-add/",
      "keywords" : "LinkList"
    } ,
  
    {
      "title"    : "初步了解Docker及其使用（一）",
      "category" : "Tool",
      
      "url"      : "https://bran-nie.github.io/2019/07/16/docker/",
      "keywords" : "Tool, docker"
    } ,
  
    {
      "title"    : "Git Pull-Request 一种名为PR的项目管理方式",
      "category" : "Tutorials",
      
      "url"      : "https://bran-nie.github.io/2020/02/28/github-PR/",
      "keywords" : "Github flow, PR"
    } ,
  
    {
      "title"    : "经济萧条下的消费",
      "category" : "Life",
      
      "url"      : "https://bran-nie.github.io/2020/04/15/think/",
      "keywords" : ""
    } ,
  
    {
      "title"    : "关于JS中, 对引用类型console出现偏差的问题分析",
      "category" : "Javascript",
      
      "url"      : "https://bran-nie.github.io/2020/04/15/console/",
      "keywords" : ""
    } ,
  
    {
      "title"    : "CSS counter 计数",
      "category" : "Css",
      
      "url"      : "https://bran-nie.github.io/2020/12/17/css-counter/",
      "keywords" : ""
    } ,
  
    {
      "title"    : "使用 css自定义属性（css变量），配合 js 更新 css，实现星星打分~",
      "category" : "Css",
      
      "url"      : "https://bran-nie.github.io/2020/12/18/css-variable/",
      "keywords" : ""
    } ,
  
    {
      "title"    : "CSS 滚动条样式",
      "category" : "Css",
      
      "url"      : "https://bran-nie.github.io/2021/01/14/scrollbar/",
      "keywords" : ""
    } ,
  
    {
      "title"    : "PicGo 一款优秀的图床",
      "category" : "Tutorials",
      
      "url"      : "https://bran-nie.github.io/2021/03/15/PicGo/",
      "keywords" : "PicGo, 图床"
    } ,
  
    {
      "title"    : "小飞机工作原理",
      "category" : "Blog",
      
      "url"      : "https://bran-nie.github.io/2021/03/22/ss/",
      "keywords" : ""
    } ,
  
    {
      "title"    : "Markdown",
      "category" : "Markdown",
      
      "url"      : "https://bran-nie.github.io/wiki/markdown/",
      "keywords" : "Markdown"
    } 
  
]

